r2gallery/__init__.py
r2gallery/const.py
r2gallery/main.py
r2gallery/model.py
r2gallery/r2.py
r2gallery/util.py
r2gallery/templates/album.toml
r2gallery/templates/album_index.html
r2gallery/templates/base.html
r2gallery/templates/gallery.toml
r2gallery/templates/index.html
r2gallery/templates/pic.html
r2gallery/templates/pics_id_list.js
r2gallery/templates/picture.toml
r2gallery-0.0.1.dist-info/entry_points.txt
r2gallery-0.0.1.dist-info/LICENSE
r2gallery-0.0.1.dist-info/WHEEL
r2gallery-0.0.1.dist-info/METADATA
r2gallery-0.0.1.dist-info/RECORD
