Metadata-Version: 2.1
Name: r2gallery
Version: 0.0.1
Summary: R2-Gallery: 个人独立相册，其中图片储存采用 Cloudflare R2 实现。
Author-email: ahui <102419@gmail.com>
Requires-Python: >=3.10
Classifier: License :: OSI Approved :: MIT License
Requires-Dist: arrow
Requires-Dist: click
Requires-Dist: jinja2
Requires-Dist: tomli
Requires-Dist: pillow
Requires-Dist: mistune
Requires-Dist: boto3
Project-URL: Home, https://github.com/ahui2016/R2-Gallery
